spytex/__init__.py
spytex/__main__.py
spytex/api.py
spytex/cli.py
spytex/compile.py
spytex/context.py
spytex/defs.py
spytex/magics.py
spytex-0.1.8.dist-info/LICENSE
spytex-0.1.8.dist-info/METADATA
spytex-0.1.8.dist-info/WHEEL
spytex-0.1.8.dist-info/entry_points.txt
spytex-0.1.8.dist-info/top_level.txt
spytex-0.1.8.dist-info/RECORD
