Metadata-Version: 2.1
Name: spytex
Version: 0.1.8
Summary: Run arbitrary Python functions indicated by JSON specs
Home-page: https://github.com/rrobby86/spytex
Author: rrobby86
Author-email: rrobby86@gmail.com
License: UNKNOWN
Platform: UNKNOWN
Classifier: Programming Language :: Python :: 3
Classifier: License :: OSI Approved :: MIT License
Classifier: Operating System :: OS Independent
Requires-Dist: smart-open (>=1.8.1)
